click_date_type/__init__.py
click_date_type-0.1.0.dist-info/LICENSE
click_date_type-0.1.0.dist-info/WHEEL
click_date_type-0.1.0.dist-info/METADATA
click_date_type-0.1.0.dist-info/RECORD
