Metadata-Version: 2.1
Name: click-date-type
Version: 0.1.0
Summary: Date type parameter for click
Home-page: https://github.com/enricobarzetti/click-date-type
Author: Enrico Barzetti
Author-email: enricobarzetti@gmail.com
Requires-Python: >=3.7,<4.0
Classifier: Programming Language :: Python :: 3
Classifier: Programming Language :: Python :: 3.7
Classifier: Programming Language :: Python :: 3.8
Requires-Dist: click (>=7.0,<8.0)
